README.rst
setup.py
whatisthis/__init__.py
whatisthis/controller.py
whatisthis/server.py
whatisthis.egg-info/PKG-INFO
whatisthis.egg-info/SOURCES.txt
whatisthis.egg-info/dependency_links.txt
whatisthis.egg-info/not-zip-safe
whatisthis.egg-info/requires.txt
whatisthis.egg-info/top_level.txt