Metadata-Version: 1.1
Name: whatisthis
Version: 0.0.2
Summary: UI for manual image classification
Home-page: http://github.com/Tom-Alexander/whatisthis
Author: Tom Alexander
Author-email: me@tomalexander.co.nz
License: MIT
Download-URL: https://github.com/Tom-Alexander/whatisthis/tarball/0.0.1
Platform: UNKNOWN
